[
  {
    "timestamp": "2026-06-28T22:07:56",
    "experiment": "step0_lr1e-3",
    "step": 0,
    "rank": 4,
    "alpha": 8,
    "scaling": 2.0,
    "lr": 0.001,
    "batch_size": 8,
    "n_trainable": 221184,
    "best_epoch": 14,
    "epochs_run": 17,
    "best_dev_ppl": 23.7514,
    "test_ppl": 21.4707,
    "test_loss": 3.0667,
    "passes_threshold": true,
    "seed": 42
  },
  {
    "timestamp": "2026-06-29T00:10:50",
    "experiment": "step0_lr5e-4",
    "step": 0,
    "rank": 4,
    "alpha": 8,
    "scaling": 2.0,
    "lr": 0.0005,
    "batch_size": 8,
    "n_trainable": 221184,
    "best_epoch": 14,
    "epochs_run": 17,
    "best_dev_ppl": 23.2654,
    "test_ppl": 21.0193,
    "test_loss": 3.0454,
    "passes_threshold": true,
    "seed": 42
  },
  {
    "timestamp": "2026-06-29T02:35:18",
    "experiment": "step0_lr1e-4",
    "step": 0,
    "rank": 4,
    "alpha": 8,
    "scaling": 2.0,
    "lr": 0.0001,
    "batch_size": 8,
    "n_trainable": 221184,
    "best_epoch": 20,
    "epochs_run": 20,
    "best_dev_ppl": 23.9456,
    "test_ppl": 21.6535,
    "test_loss": 3.0752,
    "passes_threshold": true,
    "seed": 42
  },
  {
    "timestamp": "2026-06-29T04:38:15",
    "experiment": "step1_rank4",
    "step": 1,
    "rank": 4,
    "alpha": 8,
    "scaling": 2.0,
    "lr": 0.0005,
    "batch_size": 8,
    "n_trainable": 221184,
    "best_epoch": 14,
    "epochs_run": 17,
    "best_dev_ppl": 23.2654,
    "test_ppl": 21.0193,
    "test_loss": 3.0454,
    "passes_threshold": true,
    "seed": 42
  },
  {
    "timestamp": "2026-06-29T07:02:17",
    "experiment": "step1_rank8",
    "step": 1,
    "rank": 8,
    "alpha": 16,
    "scaling": 2.0,
    "lr": 0.0005,
    "batch_size": 8,
    "n_trainable": 442368,
    "best_epoch": 19,
    "epochs_run": 20,
    "best_dev_ppl": 21.9942,
    "test_ppl": 19.9102,
    "test_loss": 2.9912,
    "passes_threshold": true,
    "seed": 42
  },
  {
    "timestamp": "2026-06-29T09:19:37",
    "experiment": "step1_rank16",
    "step": 1,
    "rank": 16,
    "alpha": 32,
    "scaling": 2.0,
    "lr": 0.0005,
    "batch_size": 8,
    "n_trainable": 884736,
    "best_epoch": 16,
    "epochs_run": 19,
    "best_dev_ppl": 21.1957,
    "test_ppl": 19.3543,
    "test_loss": 2.9629,
    "passes_threshold": true,
    "seed": 42
  },
  {
    "timestamp": "2026-06-29T11:44:06",
    "experiment": "step2_alpha_half",
    "step": 2,
    "rank": 16,
    "alpha": 8,
    "scaling": 0.5,
    "lr": 0.0005,
    "batch_size": 8,
    "n_trainable": 884736,
    "best_epoch": 19,
    "epochs_run": 20,
    "best_dev_ppl": 21.0337,
    "test_ppl": 19.1443,
    "test_loss": 2.952,
    "passes_threshold": true,
    "seed": 42
  },
  {
    "timestamp": "2026-06-29T14:08:53",
    "experiment": "step2_alpha_eq",
    "step": 2,
    "rank": 16,
    "alpha": 16,
    "scaling": 1.0,
    "lr": 0.0005,
    "batch_size": 8,
    "n_trainable": 884736,
    "best_epoch": 19,
    "epochs_run": 20,
    "best_dev_ppl": 21.0119,
    "test_ppl": 19.1497,
    "test_loss": 2.9523,
    "passes_threshold": true,
    "seed": 42
  },
  {
    "timestamp": "2026-06-29T16:26:18",
    "experiment": "step2_alpha_2x",
    "step": 2,
    "rank": 16,
    "alpha": 32,
    "scaling": 2.0,
    "lr": 0.0005,
    "batch_size": 8,
    "n_trainable": 884736,
    "best_epoch": 16,
    "epochs_run": 19,
    "best_dev_ppl": 21.1957,
    "test_ppl": 19.3543,
    "test_loss": 2.9629,
    "passes_threshold": true,
    "seed": 42
  }
]